envbee_sdk/__init__.py
envbee_sdk/constants.py
envbee_sdk/logging_config.py
envbee_sdk/main.py
envbee_sdk/metadata.py
envbee_sdk/utils.py
envbee_sdk/version.py
envbee_sdk/exceptions/__init__.py
envbee_sdk/exceptions/envbee_exceptions.py
envbee_sdk-1.8.2.dist-info/licenses/LICENSE
envbee_sdk-1.8.2.dist-info/METADATA
envbee_sdk-1.8.2.dist-info/WHEEL
envbee_sdk-1.8.2.dist-info/top_level.txt
envbee_sdk-1.8.2.dist-info/RECORD
