Metadata-Version: 2.4
Name: envbee-sdk
Version: 1.8.2
Summary: envbee SDK for Python
Home-page: https://github.com/envbee/envbee-python-sdk
Author: envbee
Author-email: info@envbee.dev
Classifier: Programming Language :: Python :: 3
Classifier: License :: OSI Approved :: MIT License
Classifier: Operating System :: OS Independent
Requires-Python: >=3.10
License-File: LICENSE
Requires-Dist: diskcache
Requires-Dist: platformdirs
Requires-Dist: requests
Requires-Dist: cryptography
Dynamic: author
Dynamic: author-email
Dynamic: classifier
Dynamic: description
Dynamic: description-content-type
Dynamic: home-page
Dynamic: license-file
Dynamic: requires-dist
Dynamic: requires-python
Dynamic: summary
